awsc/__init__.py
awsc/__main__.py
awsc/arn.py
awsc/aws.py
awsc/base_control.py
awsc/base_controls.py
awsc/commander.py
awsc/common.py
awsc/context.py
awsc/fsbrowser.py
awsc/info.py
awsc/main.py
awsc/meta.py
awsc/region.py
awsc/resource_ami.py
awsc/resource_asg.py
awsc/resource_cfn.py
awsc/resource_cloudwatch.py
awsc/resource_dsg.py
awsc/resource_ebs.py
awsc/resource_ec2.py
awsc/resource_ec2_class.py
awsc/resource_keypair.py
awsc/resource_lb.py
awsc/resource_lc.py
awsc/resource_listener.py
awsc/resource_lister.py
awsc/resource_r53.py
awsc/resource_rds.py
awsc/resource_routing.py
awsc/resource_s3.py
awsc/resource_sg.py
awsc/resource_subnet.py
awsc/resource_tg.py
awsc/resource_vpc.py
awsc/resources.py
awsc/session.py
awsc/ssh.py
awsc/config/__init__.py
awsc/config/config.py
awsc/config/scheme.py
awsc/config/storage.py
awsc/termui/__init__.py
awsc/termui/alignment.py
awsc/termui/bar_graph.py
awsc/termui/block.py
awsc/termui/color.py
awsc/termui/common.py
awsc/termui/control.py
awsc/termui/dialog.py
awsc/termui/list_control.py
awsc/termui/screen.py
awsc/termui/text_browser.py
awsc/termui/ui.py
awsc-0.3.1.dist-info/LICENSE
awsc-0.3.1.dist-info/METADATA
awsc-0.3.1.dist-info/WHEEL
awsc-0.3.1.dist-info/entry_points.txt
awsc-0.3.1.dist-info/top_level.txt
awsc-0.3.1.dist-info/RECORD
