Metadata-Version: 2.1
Name: awsc
Version: 0.3.1
Summary: AWS Commander
Home-page: https://github.com/baliame/awsc
Author: baliame
Author-email: akos.toth@cheppers.com
License: UNKNOWN
Platform: UNKNOWN
Classifier: Development Status :: 3 - Alpha
Classifier: Intended Audience :: Developers
Classifier: License :: OSI Approved :: Apache Software License
Classifier: Programming Language :: Python :: 3.8
Classifier: Programming Language :: Python :: 3 :: Only
Requires-Python: >=3.8, <4
Requires-Dist: blessed (>=1.17.12)
Requires-Dist: boto3 (>=1.16.33)
Requires-Dist: cryptography (>=3.1)
Requires-Dist: gnupg (>=1.3.2)
Requires-Dist: jq (>=1.1.1)
Requires-Dist: numpy (>=1.17.4)
Requires-Dist: pyperclip (>=1.8.1)
Requires-Dist: pyyaml (>=5.3.1)
